{
    "key": "group_63571424d9a28",
    "title": "Block: Testimonial Slides",
    "fields": [
        {
            "key": "field_635714497b8af",
            "label": "Heading",
            "name": "heading",
            "type": "text",
            "instructions": "",
            "required": 0,
            "conditional_logic": 0,
            "wrapper": {
                "width": "",
                "class": "",
                "id": ""
            },
            "default_value": "",
            "placeholder": "",
            "prepend": "",
            "append": "",
            "maxlength": ""
        },
        {
            "key": "field_635714517b8b0",
            "label": "Subheading",
            "name": "subheading",
            "type": "text",
            "instructions": "",
            "required": 0,
            "conditional_logic": 0,
            "wrapper": {
                "width": "",
                "class": "",
                "id": ""
            },
            "default_value": "",
            "placeholder": "",
            "prepend": "",
            "append": "",
            "maxlength": ""
        },
        {
            "key": "field_6357145d7b8b1",
            "label": "Testimonials",
            "name": "testimonials",
            "type": "post_object",
            "instructions": "",
            "required": 1,
            "conditional_logic": 0,
            "wrapper": {
                "width": "75",
                "class": "",
                "id": ""
            },
            "post_type": [
                "testimonials"
            ],
            "taxonomy": "",
            "allow_null": 0,
            "multiple": 1,
            "return_format": "object",
            "ui": 1
        },
        {
            "key": "field_6357148c7b8b2",
            "label": "Display",
            "name": "display",
            "type": "checkbox",
            "instructions": "",
            "required": 0,
            "conditional_logic": 0,
            "wrapper": {
                "width": "25",
                "class": "",
                "id": ""
            },
            "choices": {
                "first_name": "First name",
                "last_name": "Last name",
                "excerpt": "Excerpt",
                "quote": "Quote",
                "job_title": "Job Title",
                "company": "Company",
                "featured_image": "Featured Image"
            },
            "allow_custom": 0,
            "default_value": [
                "first_name",
                "last_name",
                "quote",
                "job_title",
                "company"
            ],
            "layout": "vertical",
            "toggle": 0,
            "return_format": "value",
            "save_custom": 0
        },
        {
            "key": "field_6357158596b51",
            "label": "Slides per View",
            "name": "slides_per_view",
            "type": "select",
            "instructions": "",
            "required": 0,
            "conditional_logic": 0,
            "wrapper": {
                "width": "25",
                "class": "",
                "id": ""
            },
            "choices": {
                "1": "1",
                "2": "2"
            },
            "default_value": 1,
            "allow_null": 0,
            "multiple": 0,
            "ui": 0,
            "return_format": "value",
            "ajax": 0,
            "placeholder": ""
        }
    ],
    "location": [
        [
            {
                "param": "block",
                "operator": "==",
                "value": "acf\/testimonial-slides"
            }
        ]
    ],
    "menu_order": 0,
    "position": "normal",
    "style": "default",
    "label_placement": "top",
    "instruction_placement": "label",
    "hide_on_screen": "",
    "active": true,
    "description": "",
    "show_in_rest": 0,
    "modified": 1666669771
}